pyBlindOpt/__init__.py
pyBlindOpt/abc_opt.py
pyBlindOpt/callback.py
pyBlindOpt/cs.py
pyBlindOpt/de.py
pyBlindOpt/egwo.py
pyBlindOpt/fa.py
pyBlindOpt/functions.py
pyBlindOpt/ga.py
pyBlindOpt/gwo.py
pyBlindOpt/hba.py
pyBlindOpt/hc.py
pyBlindOpt/hho.py
pyBlindOpt/init.py
pyBlindOpt/optimizer.py
pyBlindOpt/pso.py
pyBlindOpt/rs.py
pyBlindOpt/sa.py
pyBlindOpt/utils.py
pyblindopt-0.2.4.dist-info/licenses/LICENSE
pyblindopt-0.2.4.dist-info/METADATA
pyblindopt-0.2.4.dist-info/WHEEL
pyblindopt-0.2.4.dist-info/top_level.txt
pyblindopt-0.2.4.dist-info/RECORD
