Metadata-Version: 2.4
Name: pyBlindOpt
Version: 0.2.4
Summary: A library that implements several derivation-free optimization algorithms (such as genetic optimization).
Home-page: https://github.com/mariolpantunes/pyBlindOpt
Author: Mário Antunes
Author-email: mario.antunes@ua.pt
Classifier: Programming Language :: Python :: 3
Classifier: License :: OSI Approved :: MIT License
Classifier: Operating System :: OS Independent
Requires-Python: >=3.10
License-File: LICENSE
Requires-Dist: numpy>=1.26.0
Requires-Dist: joblib>=1.5.2
Requires-Dist: tqdm>=4.67.1
Requires-Dist: EmptySpaceSearch>=0.3.1
Dynamic: license-file
